skmultiflow/__init__.py
skmultiflow/_version.py
skmultiflow/setup.py
skmultiflow/anomaly_detection/__init__.py
skmultiflow/anomaly_detection/half_space_trees.py
skmultiflow/bayes/__init__.py
skmultiflow/bayes/naive_bayes.py
skmultiflow/bayes/utils.py
skmultiflow/core/__init__.py
skmultiflow/core/base.py
skmultiflow/core/instance_header.py
skmultiflow/core/pipeline.py
skmultiflow/data/__init__.py
skmultiflow/data/agrawal_generator.py
skmultiflow/data/anomaly_sine_generator.py
skmultiflow/data/base_stream.py
skmultiflow/data/concept_drift_stream.py
skmultiflow/data/data_stream.py
skmultiflow/data/file_stream.py
skmultiflow/data/hyper_plane_generator.py
skmultiflow/data/led_generator.py
skmultiflow/data/led_generator_drift.py
skmultiflow/data/mixed_generator.py
skmultiflow/data/multilabel_generator.py
skmultiflow/data/pseudo_random_processes.py
skmultiflow/data/random_rbf_generator.py
skmultiflow/data/random_rbf_generator_drift.py
skmultiflow/data/random_tree_generator.py
skmultiflow/data/regression_generator.py
skmultiflow/data/sea_generator.py
skmultiflow/data/sine_generator.py
skmultiflow/data/stagger_generator.py
skmultiflow/data/synth.py
skmultiflow/data/temporal_data_stream.py
skmultiflow/data/time_manager.py
skmultiflow/data/unsupervised_stream.py
skmultiflow/data/waveform_generator.py
skmultiflow/drift_detection/__init__.py
skmultiflow/drift_detection/adwin.py
skmultiflow/drift_detection/base_drift_detector.py
skmultiflow/drift_detection/ddm.py
skmultiflow/drift_detection/eddm.py
skmultiflow/drift_detection/hddm_a.py
skmultiflow/drift_detection/hddm_w.py
skmultiflow/drift_detection/kswin.py
skmultiflow/drift_detection/page_hinkley.py
skmultiflow/evaluation/__init__.py
skmultiflow/evaluation/base_evaluator.py
skmultiflow/evaluation/evaluate_holdout.py
skmultiflow/evaluation/evaluate_prequential.py
skmultiflow/evaluation/evaluate_prequential_delayed.py
skmultiflow/evaluation/evaluate_stream_gen_speed.py
skmultiflow/evaluation/evaluation_data_buffer.py
scikit_multiflow-0.5.3.dist-info/AUTHORS.md
scikit_multiflow-0.5.3.dist-info/LICENSE
scikit_multiflow-0.5.3.dist-info/METADATA
scikit_multiflow-0.5.3.dist-info/WHEEL
scikit_multiflow-0.5.3.dist-info/top_level.txt
scikit_multiflow-0.5.3.dist-info/RECORD
