Metadata-Version: 2.1
Name: scikit-multiflow
Version: 0.5.3
Summary: A machine learning package for streaming data in Python.
Home-page: https://scikit-multiflow.github.io/
Maintainer: Jacob Montiel
Maintainer-email: jacob.montiel@waikato.ac.nz
License: 3-Clause BSD
Download-URL: https://pypi.org/project/scikit-multiflow/#files
Project-URL: Documentation, https://scikit-multiflow.github.io/scikit-multiflow/
Project-URL: Source code, https://github.com/scikit-multiflow/scikit-multiflow
Project-URL: Bug Tracker, https://github.com/scikit-multiflow/scikit-multiflow/issues
Project-URL: Azure Pipelines, https://dev.azure.com/scikit-multiflow/scikit-multiflow
Platform: UNKNOWN
Classifier: Intended Audience :: Developers
Classifier: Intended Audience :: Science/Research
Classifier: Programming Language :: C
Classifier: Programming Language :: Python
Classifier: Programming Language :: Python :: 3
Classifier: Programming Language :: Python :: 3.5
Classifier: Programming Language :: Python :: 3.6
Classifier: Programming Language :: Python :: 3.7
Classifier: Programming Language :: Python :: 3.8
Classifier: Topic :: Scientific/Engineering
Classifier: Topic :: Scientific/Engineering :: Artificial Intelligence
Classifier: Topic :: Software Development
Classifier: License :: OSI Approved :: BSD License
Classifier: Operating System :: POSIX
Classifier: Operating System :: Unix
Classifier: Operating System :: MacOS
Classifier: Operating System :: Microsoft :: Windows
Requires-Python: >=3.5
Requires-Dist: sortedcontainers (>=1.5.7)
Requires-Dist: numpy (>=1.14.0)
Requires-Dist: scipy (>=1.0.0)
Requires-Dist: matplotlib (>=2.0.0)
Requires-Dist: scikit-learn (>=0.20)
Requires-Dist: pandas (>=0.25.3)
